Metadata-Version: 1.1
Name: realPython
Version: 0.1.0
Summary: This is a python package containing handy things like advanced and basic math calculations and translations.
Home-page: https://github.com/coding610/realPython
Author: Sixten Bohman
Author-email: sixten.bohman.08@gmail.com
License: apache license 2.0
Platform: UNKNOWN
Classifier: Development Status :: 1 - Planning
Classifier: Intended Audience :: Science/Research
Classifier: License :: OSI Approved :: BSD License
Classifier: Operating System :: POSIX :: Linux
Classifier: Programming Language :: Python :: 3.6
Classifier: Programming Language :: Python :: 3.7
Classifier: Programming Language :: Python :: 3.8
Classifier: Programming Language :: Python :: 3.9
